{"single_hop_efficacyq0_grad_norms": {"model.embed_tokens.weight": 35.89795684814453, "model.layers.0.self_attn.q_proj.weight": 1.278830885887146, "model.layers.0.self_attn.k_proj.weight": 1.3060424327850342, "model.layers.0.self_attn.v_proj.weight": 19.288042068481445, "model.layers.0.self_attn.o_proj.weight": 13.752870559692383, "model.layers.0.mlp.gate_proj.weight": 11.505006790161133, "model.layers.0.mlp.up_proj.weight": 12.697830200195312, "model.layers.0.mlp.down_proj.weight": 21.04427719116211, "model.layers.0.input_layernorm.weight": 1.3572804927825928, "model.layers.0.post_attention_layernorm.weight": 1.6156609058380127, "model.layers.1.self_attn.q_proj.weight": 4.033658504486084, "model.layers.1.self_attn.k_proj.weight": 2.059455633163452, "model.layers.1.self_attn.v_proj.weight": 16.05581283569336, "model.layers.1.self_attn.o_proj.weight": 9.6367769241333, "model.layers.1.mlp.gate_proj.weight": 8.393742561340332, "model.layers.1.mlp.up_proj.weight": 10.800704002380371, "model.layers.1.mlp.down_proj.weight": 97.5226058959961, "model.layers.1.input_layernorm.weight": 0.5949224829673767, "model.layers.1.post_attention_layernorm.weight": 1.0109939575195312, "model.layers.2.self_attn.q_proj.weight": 3.513148546218872, "model.layers.2.self_attn.k_proj.weight": 2.160332679748535, "model.layers.2.self_attn.v_proj.weight": 13.892515182495117, "model.layers.2.self_attn.o_proj.weight": 9.072514533996582, "model.layers.2.mlp.gate_proj.weight": 7.870990753173828, "model.layers.2.mlp.up_proj.weight": 10.996103286743164, "model.layers.2.mlp.down_proj.weight": 12.197375297546387, "model.layers.2.input_layernorm.weight": 0.5956661105155945, "model.layers.2.post_attention_layernorm.weight": 0.7954879999160767, "model.layers.3.self_attn.q_proj.weight": 3.547166347503662, "model.layers.3.self_attn.k_proj.weight": 2.729346513748169, "model.layers.3.self_attn.v_proj.weight": 12.133328437805176, "model.layers.3.self_attn.o_proj.weight": 9.508118629455566, "model.layers.3.mlp.gate_proj.weight": 6.697222709655762, "model.layers.3.mlp.up_proj.weight": 13.233939170837402, "model.layers.3.mlp.down_proj.weight": 12.390050888061523, "model.layers.3.input_layernorm.weight": 1.6876132488250732, "model.layers.3.post_attention_layernorm.weight": 0.7826950550079346, "model.layers.4.self_attn.q_proj.weight": 5.304009437561035, "model.layers.4.self_attn.k_proj.weight": 2.37682843208313, "model.layers.4.self_attn.v_proj.weight": 10.59574031829834, "model.layers.4.self_attn.o_proj.weight": 11.009378433227539, "model.layers.4.mlp.gate_proj.weight": 5.542423248291016, "model.layers.4.mlp.up_proj.weight": 11.709027290344238, "model.layers.4.mlp.down_proj.weight": 10.918596267700195, "model.layers.4.input_layernorm.weight": 0.46909794211387634, "model.layers.4.post_attention_layernorm.weight": 0.7059106230735779, "model.layers.5.self_attn.q_proj.weight": 3.3771779537200928, "model.layers.5.self_attn.k_proj.weight": 1.951586365699768, "model.layers.5.self_attn.v_proj.weight": 7.705755710601807, "model.layers.5.self_attn.o_proj.weight": 9.902395248413086, "model.layers.5.mlp.gate_proj.weight": 5.19182014465332, "model.layers.5.mlp.up_proj.weight": 9.452566146850586, "model.layers.5.mlp.down_proj.weight": 9.16346263885498, "model.layers.5.input_layernorm.weight": 0.40355852246284485, "model.layers.5.post_attention_layernorm.weight": 0.5386822819709778, "model.layers.6.self_attn.q_proj.weight": 2.9115982055664062, "model.layers.6.self_attn.k_proj.weight": 1.4780056476593018, "model.layers.6.self_attn.v_proj.weight": 6.702573299407959, "model.layers.6.self_attn.o_proj.weight": 9.693316459655762, "model.layers.6.mlp.gate_proj.weight": 4.587162971496582, "model.layers.6.mlp.up_proj.weight": 7.595025539398193, "model.layers.6.mlp.down_proj.weight": 8.666897773742676, "model.layers.6.input_layernorm.weight": 0.38394930958747864, "model.layers.6.post_attention_layernorm.weight": 0.5132545232772827, "model.layers.7.self_attn.q_proj.weight": 3.092360734939575, "model.layers.7.self_attn.k_proj.weight": 1.5999164581298828, "model.layers.7.self_attn.v_proj.weight": 6.8977742195129395, "model.layers.7.self_attn.o_proj.weight": 9.22984790802002, "model.layers.7.mlp.gate_proj.weight": 4.5114641189575195, "model.layers.7.mlp.up_proj.weight": 7.613251209259033, "model.layers.7.mlp.down_proj.weight": 8.651823043823242, "model.layers.7.input_layernorm.weight": 0.21586363017559052, "model.layers.7.post_attention_layernorm.weight": 0.5131873488426208, "model.layers.8.self_attn.q_proj.weight": 2.157554864883423, "model.layers.8.self_attn.k_proj.weight": 1.248311161994934, "model.layers.8.self_attn.v_proj.weight": 8.279934883117676, "model.layers.8.self_attn.o_proj.weight": 8.801472663879395, "model.layers.8.mlp.gate_proj.weight": 4.6456685066223145, "model.layers.8.mlp.up_proj.weight": 8.252097129821777, "model.layers.8.mlp.down_proj.weight": 9.659164428710938, "model.layers.8.input_layernorm.weight": 0.30164530873298645, "model.layers.8.post_attention_layernorm.weight": 0.5040282011032104, "model.layers.9.self_attn.q_proj.weight": 2.4657466411590576, "model.layers.9.self_attn.k_proj.weight": 1.4898691177368164, "model.layers.9.self_attn.v_proj.weight": 10.559800148010254, "model.layers.9.self_attn.o_proj.weight": 8.32622241973877, "model.layers.9.mlp.gate_proj.weight": 5.002931118011475, "model.layers.9.mlp.up_proj.weight": 8.5891695022583, "model.layers.9.mlp.down_proj.weight": 11.183205604553223, "model.layers.9.input_layernorm.weight": 0.31953752040863037, "model.layers.9.post_attention_layernorm.weight": 0.48153752088546753, "model.layers.10.self_attn.q_proj.weight": 2.005842685699463, "model.layers.10.self_attn.k_proj.weight": 1.5561603307724, "model.layers.10.self_attn.v_proj.weight": 8.910689353942871, "model.layers.10.self_attn.o_proj.weight": 8.217974662780762, "model.layers.10.mlp.gate_proj.weight": 5.817477703094482, "model.layers.10.mlp.up_proj.weight": 9.556920051574707, "model.layers.10.mlp.down_proj.weight": 12.213229179382324, "model.layers.10.input_layernorm.weight": 0.2218088060617447, "model.layers.10.post_attention_layernorm.weight": 0.47481247782707214, "model.layers.11.self_attn.q_proj.weight": 2.4478988647460938, "model.layers.11.self_attn.k_proj.weight": 1.5310670137405396, "model.layers.11.self_attn.v_proj.weight": 8.679937362670898, "model.layers.11.self_attn.o_proj.weight": 7.178188323974609, "model.layers.11.mlp.gate_proj.weight": 6.258906841278076, "model.layers.11.mlp.up_proj.weight": 9.68612289428711, "model.layers.11.mlp.down_proj.weight": 13.482697486877441, "model.layers.11.input_layernorm.weight": 0.3009102940559387, "model.layers.11.post_attention_layernorm.weight": 0.5046828985214233, "model.layers.12.self_attn.q_proj.weight": 2.4500012397766113, "model.layers.12.self_attn.k_proj.weight": 1.8883247375488281, "model.layers.12.self_attn.v_proj.weight": 11.850844383239746, "model.layers.12.self_attn.o_proj.weight": 6.2001190185546875, "model.layers.12.mlp.gate_proj.weight": 8.251392364501953, "model.layers.12.mlp.up_proj.weight": 9.758474349975586, "model.layers.12.mlp.down_proj.weight": 11.553812980651855, "model.layers.12.input_layernorm.weight": 0.33631521463394165, "model.layers.12.post_attention_layernorm.weight": 0.5513353943824768, "model.layers.13.self_attn.q_proj.weight": 2.8877341747283936, "model.layers.13.self_attn.k_proj.weight": 1.2542827129364014, "model.layers.13.self_attn.v_proj.weight": 7.439603328704834, "model.layers.13.self_attn.o_proj.weight": 5.030925273895264, "model.layers.13.mlp.gate_proj.weight": 9.096830368041992, "model.layers.13.mlp.up_proj.weight": 9.85175609588623, "model.layers.13.mlp.down_proj.weight": 13.391225814819336, "model.layers.13.input_layernorm.weight": 0.29036790132522583, "model.layers.13.post_attention_layernorm.weight": 0.5925511121749878, "model.layers.14.self_attn.q_proj.weight": 2.489957094192505, "model.layers.14.self_attn.k_proj.weight": 1.8443903923034668, "model.layers.14.self_attn.v_proj.weight": 8.094313621520996, "model.layers.14.self_attn.o_proj.weight": 3.670309543609619, "model.layers.14.mlp.gate_proj.weight": 8.58878231048584, "model.layers.14.mlp.up_proj.weight": 8.55168628692627, "model.layers.14.mlp.down_proj.weight": 11.44171142578125, "model.layers.14.input_layernorm.weight": 0.34998053312301636, "model.layers.14.post_attention_layernorm.weight": 0.6404204964637756, "model.layers.15.self_attn.q_proj.weight": 3.2492661476135254, "model.layers.15.self_attn.k_proj.weight": 1.4078084230422974, "model.layers.15.self_attn.v_proj.weight": 5.615213871002197, "model.layers.15.self_attn.o_proj.weight": 8.332184791564941, "model.layers.15.mlp.gate_proj.weight": 7.9027581214904785, "model.layers.15.mlp.up_proj.weight": 24.924406051635742, "model.layers.15.mlp.down_proj.weight": 20.063016891479492, "model.layers.15.input_layernorm.weight": 0.27355214953422546, "model.layers.15.post_attention_layernorm.weight": 1.0008792877197266, "model.norm.weight": 0.22993351519107819}, "single_hop_efficacyq1_grad_norms": {"model.embed_tokens.weight": 81.10490417480469, "model.layers.0.self_attn.q_proj.weight": 4.294163703918457, "model.layers.0.self_attn.k_proj.weight": 4.261534214019775, "model.layers.0.self_attn.v_proj.weight": 87.23931884765625, "model.layers.0.self_attn.o_proj.weight": 57.66289520263672, "model.layers.0.mlp.gate_proj.weight": 40.5389518737793, "model.layers.0.mlp.up_proj.weight": 50.51268768310547, "model.layers.0.mlp.down_proj.weight": 81.79391479492188, "model.layers.0.input_layernorm.weight": 3.431083917617798, "model.layers.0.post_attention_layernorm.weight": 5.753139495849609, "model.layers.1.self_attn.q_proj.weight": 13.197409629821777, "model.layers.1.self_attn.k_proj.weight": 8.06364631652832, "model.layers.1.self_attn.v_proj.weight": 63.080631256103516, "model.layers.1.self_attn.o_proj.weight": 41.08360290527344, "model.layers.1.mlp.gate_proj.weight": 36.43963623046875, "model.layers.1.mlp.up_proj.weight": 46.381072998046875, "model.layers.1.mlp.down_proj.weight": 268.2911682128906, "model.layers.1.input_layernorm.weight": 1.50813889503479, "model.layers.1.post_attention_layernorm.weight": 4.119252681732178, "model.layers.2.self_attn.q_proj.weight": 14.509968757629395, "model.layers.2.self_attn.k_proj.weight": 10.778592109680176, "model.layers.2.self_attn.v_proj.weight": 50.668312072753906, "model.layers.2.self_attn.o_proj.weight": 35.857059478759766, "model.layers.2.mlp.gate_proj.weight": 31.974973678588867, "model.layers.2.mlp.up_proj.weight": 44.53892517089844, "model.layers.2.mlp.down_proj.weight": 44.975467681884766, "model.layers.2.input_layernorm.weight": 2.8993942737579346, "model.layers.2.post_attention_layernorm.weight": 3.3367183208465576, "model.layers.3.self_attn.q_proj.weight": 14.705534934997559, "model.layers.3.self_attn.k_proj.weight": 11.058029174804688, "model.layers.3.self_attn.v_proj.weight": 45.96903991699219, "model.layers.3.self_attn.o_proj.weight": 34.51658248901367, "model.layers.3.mlp.gate_proj.weight": 26.433740615844727, "model.layers.3.mlp.up_proj.weight": 43.825233459472656, "model.layers.3.mlp.down_proj.weight": 45.228553771972656, "model.layers.3.input_layernorm.weight": 2.0866379737854004, "model.layers.3.post_attention_layernorm.weight": 2.7219676971435547, "model.layers.4.self_attn.q_proj.weight": 22.242300033569336, "model.layers.4.self_attn.k_proj.weight": 11.56279182434082, "model.layers.4.self_attn.v_proj.weight": 37.75625991821289, "model.layers.4.self_attn.o_proj.weight": 38.15202331542969, "model.layers.4.mlp.gate_proj.weight": 21.596450805664062, "model.layers.4.mlp.up_proj.weight": 42.74618911743164, "model.layers.4.mlp.down_proj.weight": 41.74315643310547, "model.layers.4.input_layernorm.weight": 4.384925842285156, "model.layers.4.post_attention_layernorm.weight": 2.720733642578125, "model.layers.5.self_attn.q_proj.weight": 17.171964645385742, "model.layers.5.self_attn.k_proj.weight": 9.217281341552734, "model.layers.5.self_attn.v_proj.weight": 35.0666389465332, "model.layers.5.self_attn.o_proj.weight": 35.725860595703125, "model.layers.5.mlp.gate_proj.weight": 20.41720199584961, "model.layers.5.mlp.up_proj.weight": 35.60305404663086, "model.layers.5.mlp.down_proj.weight": 36.77864456176758, "model.layers.5.input_layernorm.weight": 1.0810463428497314, "model.layers.5.post_attention_layernorm.weight": 2.2002668380737305, "model.layers.6.self_attn.q_proj.weight": 15.597236633300781, "model.layers.6.self_attn.k_proj.weight": 7.519615173339844, "model.layers.6.self_attn.v_proj.weight": 27.317245483398438, "model.layers.6.self_attn.o_proj.weight": 41.13349914550781, "model.layers.6.mlp.gate_proj.weight": 18.341691970825195, "model.layers.6.mlp.up_proj.weight": 34.09929656982422, "model.layers.6.mlp.down_proj.weight": 34.051334381103516, "model.layers.6.input_layernorm.weight": 0.8919684886932373, "model.layers.6.post_attention_layernorm.weight": 1.9706109762191772, "model.layers.7.self_attn.q_proj.weight": 10.591485023498535, "model.layers.7.self_attn.k_proj.weight": 6.430672645568848, "model.layers.7.self_attn.v_proj.weight": 29.336563110351562, "model.layers.7.self_attn.o_proj.weight": 33.53253936767578, "model.layers.7.mlp.gate_proj.weight": 19.914527893066406, "model.layers.7.mlp.up_proj.weight": 32.060420989990234, "model.layers.7.mlp.down_proj.weight": 28.447696685791016, "model.layers.7.input_layernorm.weight": 1.0532810688018799, "model.layers.7.post_attention_layernorm.weight": 2.269923448562622, "model.layers.8.self_attn.q_proj.weight": 14.020795822143555, "model.layers.8.self_attn.k_proj.weight": 9.514904975891113, "model.layers.8.self_attn.v_proj.weight": 29.97749137878418, "model.layers.8.self_attn.o_proj.weight": 29.58017349243164, "model.layers.8.mlp.gate_proj.weight": 16.806507110595703, "model.layers.8.mlp.up_proj.weight": 27.518760681152344, "model.layers.8.mlp.down_proj.weight": 25.748144149780273, "model.layers.8.input_layernorm.weight": 2.344264268875122, "model.layers.8.post_attention_layernorm.weight": 1.9540480375289917, "model.layers.9.self_attn.q_proj.weight": 10.675594329833984, "model.layers.9.self_attn.k_proj.weight": 8.043298721313477, "model.layers.9.self_attn.v_proj.weight": 22.31133460998535, "model.layers.9.self_attn.o_proj.weight": 21.944900512695312, "model.layers.9.mlp.gate_proj.weight": 12.40399169921875, "model.layers.9.mlp.up_proj.weight": 21.70532989501953, "model.layers.9.mlp.down_proj.weight": 23.50423240661621, "model.layers.9.input_layernorm.weight": 1.5179399251937866, "model.layers.9.post_attention_layernorm.weight": 1.1891025304794312, "model.layers.10.self_attn.q_proj.weight": 10.495244026184082, "model.layers.10.self_attn.k_proj.weight": 8.565974235534668, "model.layers.10.self_attn.v_proj.weight": 17.380125045776367, "model.layers.10.self_attn.o_proj.weight": 16.190513610839844, "model.layers.10.mlp.gate_proj.weight": 11.12015438079834, "model.layers.10.mlp.up_proj.weight": 17.022401809692383, "model.layers.10.mlp.down_proj.weight": 18.709266662597656, "model.layers.10.input_layernorm.weight": 0.865972638130188, "model.layers.10.post_attention_layernorm.weight": 0.8934676647186279, "model.layers.11.self_attn.q_proj.weight": 4.733509540557861, "model.layers.11.self_attn.k_proj.weight": 3.0840775966644287, "model.layers.11.self_attn.v_proj.weight": 13.589927673339844, "model.layers.11.self_attn.o_proj.weight": 14.41472053527832, "model.layers.11.mlp.gate_proj.weight": 10.420035362243652, "model.layers.11.mlp.up_proj.weight": 14.904335021972656, "model.layers.11.mlp.down_proj.weight": 17.589147567749023, "model.layers.11.input_layernorm.weight": 0.9848446249961853, "model.layers.11.post_attention_layernorm.weight": 0.798095166683197, "model.layers.12.self_attn.q_proj.weight": 7.858301639556885, "model.layers.12.self_attn.k_proj.weight": 4.454928398132324, "model.layers.12.self_attn.v_proj.weight": 15.315375328063965, "model.layers.12.self_attn.o_proj.weight": 10.729549407958984, "model.layers.12.mlp.gate_proj.weight": 10.269308090209961, "model.layers.12.mlp.up_proj.weight": 12.6752290725708, "model.layers.12.mlp.down_proj.weight": 17.46334457397461, "model.layers.12.input_layernorm.weight": 1.173234224319458, "model.layers.12.post_attention_layernorm.weight": 0.6617426872253418, "model.layers.13.self_attn.q_proj.weight": 4.765349864959717, "model.layers.13.self_attn.k_proj.weight": 2.365135908126831, "model.layers.13.self_attn.v_proj.weight": 12.275392532348633, "model.layers.13.self_attn.o_proj.weight": 9.54593276977539, "model.layers.13.mlp.gate_proj.weight": 10.848621368408203, "model.layers.13.mlp.up_proj.weight": 13.072973251342773, "model.layers.13.mlp.down_proj.weight": 18.675378799438477, "model.layers.13.input_layernorm.weight": 0.42199140787124634, "model.layers.13.post_attention_layernorm.weight": 0.6878483295440674, "model.layers.14.self_attn.q_proj.weight": 4.196573257446289, "model.layers.14.self_attn.k_proj.weight": 3.7248923778533936, "model.layers.14.self_attn.v_proj.weight": 15.455086708068848, "model.layers.14.self_attn.o_proj.weight": 10.588273048400879, "model.layers.14.mlp.gate_proj.weight": 9.74585247039795, "model.layers.14.mlp.up_proj.weight": 10.875191688537598, "model.layers.14.mlp.down_proj.weight": 16.531158447265625, "model.layers.14.input_layernorm.weight": 0.5123198628425598, "model.layers.14.post_attention_layernorm.weight": 0.9888313412666321, "model.layers.15.self_attn.q_proj.weight": 7.141460418701172, "model.layers.15.self_attn.k_proj.weight": 4.538637638092041, "model.layers.15.self_attn.v_proj.weight": 10.603904724121094, "model.layers.15.self_attn.o_proj.weight": 17.66265869140625, "model.layers.15.mlp.gate_proj.weight": 11.930302619934082, "model.layers.15.mlp.up_proj.weight": 18.963279724121094, "model.layers.15.mlp.down_proj.weight": 30.31615447998047, "model.layers.15.input_layernorm.weight": 0.5506406426429749, "model.layers.15.post_attention_layernorm.weight": 1.090806484222412, "model.norm.weight": 0.3296130299568176}, "multi_hop_efficacyq0_grad_norms": {"model.embed_tokens.weight": 37.610206604003906, "model.layers.0.self_attn.q_proj.weight": 1.8614773750305176, "model.layers.0.self_attn.k_proj.weight": 1.96945059299469, "model.layers.0.self_attn.v_proj.weight": 29.733808517456055, "model.layers.0.self_attn.o_proj.weight": 19.309694290161133, "model.layers.0.mlp.gate_proj.weight": 12.793182373046875, "model.layers.0.mlp.up_proj.weight": 15.384946823120117, "model.layers.0.mlp.down_proj.weight": 25.37925910949707, "model.layers.0.input_layernorm.weight": 3.274496555328369, "model.layers.0.post_attention_layernorm.weight": 1.7306004762649536, "model.layers.1.self_attn.q_proj.weight": 5.849340915679932, "model.layers.1.self_attn.k_proj.weight": 3.932504415512085, "model.layers.1.self_attn.v_proj.weight": 21.574861526489258, "model.layers.1.self_attn.o_proj.weight": 14.083325386047363, "model.layers.1.mlp.gate_proj.weight": 11.57833480834961, "model.layers.1.mlp.up_proj.weight": 14.707914352416992, "model.layers.1.mlp.down_proj.weight": 105.80329895019531, "model.layers.1.input_layernorm.weight": 1.347025990486145, "model.layers.1.post_attention_layernorm.weight": 1.3322170972824097, "model.layers.2.self_attn.q_proj.weight": 5.075222492218018, "model.layers.2.self_attn.k_proj.weight": 3.359036684036255, "model.layers.2.self_attn.v_proj.weight": 17.924650192260742, "model.layers.2.self_attn.o_proj.weight": 11.06554889678955, "model.layers.2.mlp.gate_proj.weight": 10.463306427001953, "model.layers.2.mlp.up_proj.weight": 14.623669624328613, "model.layers.2.mlp.down_proj.weight": 16.106327056884766, "model.layers.2.input_layernorm.weight": 1.1021755933761597, "model.layers.2.post_attention_layernorm.weight": 1.102897047996521, "model.layers.3.self_attn.q_proj.weight": 4.894957065582275, "model.layers.3.self_attn.k_proj.weight": 3.999657154083252, "model.layers.3.self_attn.v_proj.weight": 15.860208511352539, "model.layers.3.self_attn.o_proj.weight": 11.837549209594727, "model.layers.3.mlp.gate_proj.weight": 8.519078254699707, "model.layers.3.mlp.up_proj.weight": 15.469529151916504, "model.layers.3.mlp.down_proj.weight": 15.697550773620605, "model.layers.3.input_layernorm.weight": 3.5613346099853516, "model.layers.3.post_attention_layernorm.weight": 0.9776676893234253, "model.layers.4.self_attn.q_proj.weight": 5.175910472869873, "model.layers.4.self_attn.k_proj.weight": 2.8323683738708496, "model.layers.4.self_attn.v_proj.weight": 14.431801795959473, "model.layers.4.self_attn.o_proj.weight": 14.427023887634277, "model.layers.4.mlp.gate_proj.weight": 7.079627513885498, "model.layers.4.mlp.up_proj.weight": 15.625113487243652, "model.layers.4.mlp.down_proj.weight": 15.075386047363281, "model.layers.4.input_layernorm.weight": 0.4432879090309143, "model.layers.4.post_attention_layernorm.weight": 0.920032262802124, "model.layers.5.self_attn.q_proj.weight": 4.69101095199585, "model.layers.5.self_attn.k_proj.weight": 2.604823589324951, "model.layers.5.self_attn.v_proj.weight": 11.718642234802246, "model.layers.5.self_attn.o_proj.weight": 13.918974876403809, "model.layers.5.mlp.gate_proj.weight": 7.318260669708252, "model.layers.5.mlp.up_proj.weight": 12.784177780151367, "model.layers.5.mlp.down_proj.weight": 13.204638481140137, "model.layers.5.input_layernorm.weight": 0.321347177028656, "model.layers.5.post_attention_layernorm.weight": 0.7808307409286499, "model.layers.6.self_attn.q_proj.weight": 6.606180667877197, "model.layers.6.self_attn.k_proj.weight": 2.944957733154297, "model.layers.6.self_attn.v_proj.weight": 10.303874969482422, "model.layers.6.self_attn.o_proj.weight": 15.037574768066406, "model.layers.6.mlp.gate_proj.weight": 6.490572452545166, "model.layers.6.mlp.up_proj.weight": 11.282382011413574, "model.layers.6.mlp.down_proj.weight": 11.441787719726562, "model.layers.6.input_layernorm.weight": 0.39219024777412415, "model.layers.6.post_attention_layernorm.weight": 0.6537079811096191, "model.layers.7.self_attn.q_proj.weight": 4.560375690460205, "model.layers.7.self_attn.k_proj.weight": 2.049171209335327, "model.layers.7.self_attn.v_proj.weight": 10.086322784423828, "model.layers.7.self_attn.o_proj.weight": 12.822615623474121, "model.layers.7.mlp.gate_proj.weight": 6.459176540374756, "model.layers.7.mlp.up_proj.weight": 10.431734085083008, "model.layers.7.mlp.down_proj.weight": 10.870623588562012, "model.layers.7.input_layernorm.weight": 0.4660845100879669, "model.layers.7.post_attention_layernorm.weight": 0.6726419925689697, "model.layers.8.self_attn.q_proj.weight": 5.228302001953125, "model.layers.8.self_attn.k_proj.weight": 2.5883991718292236, "model.layers.8.self_attn.v_proj.weight": 11.644363403320312, "model.layers.8.self_attn.o_proj.weight": 10.983098983764648, "model.layers.8.mlp.gate_proj.weight": 6.035864353179932, "model.layers.8.mlp.up_proj.weight": 11.124306678771973, "model.layers.8.mlp.down_proj.weight": 10.561287879943848, "model.layers.8.input_layernorm.weight": 0.3367931842803955, "model.layers.8.post_attention_layernorm.weight": 0.5907760262489319, "model.layers.9.self_attn.q_proj.weight": 3.3915135860443115, "model.layers.9.self_attn.k_proj.weight": 2.266165256500244, "model.layers.9.self_attn.v_proj.weight": 9.964150428771973, "model.layers.9.self_attn.o_proj.weight": 9.046464920043945, "model.layers.9.mlp.gate_proj.weight": 5.783202648162842, "model.layers.9.mlp.up_proj.weight": 9.784246444702148, "model.layers.9.mlp.down_proj.weight": 11.256610870361328, "model.layers.9.input_layernorm.weight": 0.5993275046348572, "model.layers.9.post_attention_layernorm.weight": 0.6580793857574463, "model.layers.10.self_attn.q_proj.weight": 4.718828201293945, "model.layers.10.self_attn.k_proj.weight": 3.6155197620391846, "model.layers.10.self_attn.v_proj.weight": 8.205057144165039, "model.layers.10.self_attn.o_proj.weight": 7.9448466300964355, "model.layers.10.mlp.gate_proj.weight": 5.402209281921387, "model.layers.10.mlp.up_proj.weight": 8.712355613708496, "model.layers.10.mlp.down_proj.weight": 10.003087997436523, "model.layers.10.input_layernorm.weight": 0.41836538910865784, "model.layers.10.post_attention_layernorm.weight": 0.5745116472244263, "model.layers.11.self_attn.q_proj.weight": 2.1724326610565186, "model.layers.11.self_attn.k_proj.weight": 1.5407975912094116, "model.layers.11.self_attn.v_proj.weight": 8.161468505859375, "model.layers.11.self_attn.o_proj.weight": 7.04274845123291, "model.layers.11.mlp.gate_proj.weight": 5.451372146606445, "model.layers.11.mlp.up_proj.weight": 7.899693965911865, "model.layers.11.mlp.down_proj.weight": 10.101577758789062, "model.layers.11.input_layernorm.weight": 0.23698225617408752, "model.layers.11.post_attention_layernorm.weight": 0.4191092848777771, "model.layers.12.self_attn.q_proj.weight": 2.2541439533233643, "model.layers.12.self_attn.k_proj.weight": 1.5071619749069214, "model.layers.12.self_attn.v_proj.weight": 8.601423263549805, "model.layers.12.self_attn.o_proj.weight": 5.8463945388793945, "model.layers.12.mlp.gate_proj.weight": 5.574138641357422, "model.layers.12.mlp.up_proj.weight": 6.824317455291748, "model.layers.12.mlp.down_proj.weight": 9.368062973022461, "model.layers.12.input_layernorm.weight": 0.30614620447158813, "model.layers.12.post_attention_layernorm.weight": 0.3897278606891632, "model.layers.13.self_attn.q_proj.weight": 3.3249125480651855, "model.layers.13.self_attn.k_proj.weight": 1.3245749473571777, "model.layers.13.self_attn.v_proj.weight": 7.5958476066589355, "model.layers.13.self_attn.o_proj.weight": 5.9085693359375, "model.layers.13.mlp.gate_proj.weight": 6.808698654174805, "model.layers.13.mlp.up_proj.weight": 7.695162296295166, "model.layers.13.mlp.down_proj.weight": 11.259217262268066, "model.layers.13.input_layernorm.weight": 0.18539723753929138, "model.layers.13.post_attention_layernorm.weight": 0.4456719756126404, "model.layers.14.self_attn.q_proj.weight": 2.110679864883423, "model.layers.14.self_attn.k_proj.weight": 1.7016682624816895, "model.layers.14.self_attn.v_proj.weight": 7.398017883300781, "model.layers.14.self_attn.o_proj.weight": 4.904200553894043, "model.layers.14.mlp.gate_proj.weight": 6.454281330108643, "model.layers.14.mlp.up_proj.weight": 6.734347820281982, "model.layers.14.mlp.down_proj.weight": 10.542197227478027, "model.layers.14.input_layernorm.weight": 0.5065520405769348, "model.layers.14.post_attention_layernorm.weight": 0.4460279941558838, "model.layers.15.self_attn.q_proj.weight": 2.3239994049072266, "model.layers.15.self_attn.k_proj.weight": 2.0211069583892822, "model.layers.15.self_attn.v_proj.weight": 6.221290588378906, "model.layers.15.self_attn.o_proj.weight": 8.84992504119873, "model.layers.15.mlp.gate_proj.weight": 8.630374908447266, "model.layers.15.mlp.up_proj.weight": 17.980979919433594, "model.layers.15.mlp.down_proj.weight": 22.356468200683594, "model.layers.15.input_layernorm.weight": 0.498320072889328, "model.layers.15.post_attention_layernorm.weight": 0.7336710691452026, "model.norm.weight": 0.26890286803245544}, "interpolation_t": {"model.embed_tokens.weight": 0.23807312548160553, "model.layers.0.self_attn.q_proj.weight": 0.050363071262836456, "model.layers.0.self_attn.k_proj.weight": 0.04767467454075813, "model.layers.0.self_attn.v_proj.weight": 0.03930952399969101, "model.layers.0.self_attn.o_proj.weight": 0.056899696588516235, "model.layers.0.mlp.gate_proj.weight": 0.07235846668481827, "model.layers.0.mlp.up_proj.weight": 0.055693916976451874, "model.layers.0.mlp.down_proj.weight": 0.04729436710476875, "model.layers.0.input_layernorm.weight": 0.15662333369255066, "model.layers.0.post_attention_layernorm.weight": 0.07337865978479385, "model.layers.1.self_attn.q_proj.weight": 0.09850520640611649, "model.layers.1.self_attn.k_proj.weight": 0.08786274492740631, "model.layers.1.self_attn.v_proj.weight": 0.05859806016087532, "model.layers.1.self_attn.o_proj.weight": 0.0594002790749073, "model.layers.1.mlp.gate_proj.weight": 0.048403654247522354, "model.layers.1.mlp.up_proj.weight": 0.048817481845617294, "model.layers.1.mlp.down_proj.weight": 0.14174485206604004, "model.layers.1.input_layernorm.weight": -0.27886781096458435, "model.layers.1.post_attention_layernorm.weight": 0.07099948823451996, "model.layers.2.self_attn.q_proj.weight": 0.048959314823150635, "model.layers.2.self_attn.k_proj.weight": -0.02623451128602028, "model.layers.2.self_attn.v_proj.weight": 0.06614552438259125, "model.layers.2.self_attn.o_proj.weight": 0.07370524108409882, "model.layers.2.mlp.gate_proj.weight": 0.06339134275913239, "model.layers.2.mlp.up_proj.weight": 0.06637740880250931, "model.layers.2.mlp.down_proj.weight": 0.08405162394046783, "model.layers.2.input_layernorm.weight": -0.13751310110092163, "model.layers.2.post_attention_layernorm.weight": 0.0511925034224987, "model.layers.3.self_attn.q_proj.weight": 0.033311840146780014, "model.layers.3.self_attn.k_proj.weight": 0.09634481370449066, "model.layers.3.self_attn.v_proj.weight": 0.11459831148386002, "model.layers.3.self_attn.o_proj.weight": 0.09620039910078049, "model.layers.3.mlp.gate_proj.weight": 0.06346770375967026, "model.layers.3.mlp.up_proj.weight": 0.10195586085319519, "model.layers.3.mlp.down_proj.weight": 0.08086567372083664, "model.layers.3.input_layernorm.weight": 1.368637204170227, "model.layers.3.post_attention_layernorm.weight": 0.09144221991300583, "model.layers.4.self_attn.q_proj.weight": 0.03600762039422989, "model.layers.4.self_attn.k_proj.weight": -0.0321878157556057, "model.layers.4.self_attn.v_proj.weight": 0.08787515759468079, "model.layers.4.self_attn.o_proj.weight": 0.10400840640068054, "model.layers.4.mlp.gate_proj.weight": 0.0711129754781723, "model.layers.4.mlp.up_proj.weight": 0.09641803801059723, "model.layers.4.mlp.down_proj.weight": 0.0963207483291626, "model.layers.4.input_layernorm.weight": -0.139163076877594, "model.layers.4.post_attention_layernorm.weight": 0.06851275265216827, "model.layers.5.self_attn.q_proj.weight": 0.0496060848236084, "model.layers.5.self_attn.k_proj.weight": 0.03909974545240402, "model.layers.5.self_attn.v_proj.weight": 0.06647537648677826, "model.layers.5.self_attn.o_proj.weight": 0.12666581571102142, "model.layers.5.mlp.gate_proj.weight": 0.07538820803165436, "model.layers.5.mlp.up_proj.weight": 0.10252508521080017, "model.layers.5.mlp.down_proj.weight": 0.09744338691234589, "model.layers.5.input_layernorm.weight": 0.31496039032936096, "model.layers.5.post_attention_layernorm.weight": 0.04569924622774124, "model.layers.6.self_attn.q_proj.weight": 0.050466619431972504, "model.layers.6.self_attn.k_proj.weight": 0.03691286966204643, "model.layers.6.self_attn.v_proj.weight": 0.09025827795267105, "model.layers.6.self_attn.o_proj.weight": 0.10146389901638031, "model.layers.6.mlp.gate_proj.weight": 0.09100215882062912, "model.layers.6.mlp.up_proj.weight": 0.08115290105342865, "model.layers.6.mlp.down_proj.weight": 0.0939163938164711, "model.layers.6.input_layernorm.weight": -0.001992700155824423, "model.layers.6.post_attention_layernorm.weight": 0.0918758288025856, "model.layers.7.self_attn.q_proj.weight": 0.09793226420879364, "model.layers.7.self_attn.k_proj.weight": 0.07869412004947662, "model.layers.7.self_attn.v_proj.weight": 0.08017046749591827, "model.layers.7.self_attn.o_proj.weight": 0.11701209843158722, "model.layers.7.mlp.gate_proj.weight": 0.07446921616792679, "model.layers.7.mlp.up_proj.weight": 0.0882519781589508, "model.layers.7.mlp.down_proj.weight": 0.13116636872291565, "model.layers.7.input_layernorm.weight": -0.3154664635658264, "model.layers.7.post_attention_layernorm.weight": 0.12529560923576355, "model.layers.8.self_attn.q_proj.weight": 0.014113004319369793, "model.layers.8.self_attn.k_proj.weight": 0.04979819059371948, "model.layers.8.self_attn.v_proj.weight": 0.10608695447444916, "model.layers.8.self_attn.o_proj.weight": 0.11622650176286697, "model.layers.8.mlp.gate_proj.weight": 0.1149052307009697, "model.layers.8.mlp.up_proj.weight": 0.14896820485591888, "model.layers.8.mlp.down_proj.weight": 0.18070240318775177, "model.layers.8.input_layernorm.weight": -0.11654597520828247, "model.layers.8.post_attention_layernorm.weight": 0.14631947875022888, "model.layers.9.self_attn.q_proj.weight": 0.0638599619269371, "model.layers.9.self_attn.k_proj.weight": 0.04589173197746277, "model.layers.9.self_attn.v_proj.weight": 0.20426644384860992, "model.layers.9.self_attn.o_proj.weight": 0.16659170389175415, "model.layers.9.mlp.gate_proj.weight": 0.201337069272995, "model.layers.9.mlp.up_proj.weight": 0.2218828797340393, "model.layers.9.mlp.down_proj.weight": 0.26056981086730957, "model.layers.9.input_layernorm.weight": 0.25530529022216797, "model.layers.9.post_attention_layernorm.weight": 0.17288698256015778, "model.layers.10.self_attn.q_proj.weight": 0.13394199311733246, "model.layers.10.self_attn.k_proj.weight": 0.093286894261837, "model.layers.10.self_attn.v_proj.weight": 0.22411127388477325, "model.layers.10.self_attn.o_proj.weight": 0.26588329672813416, "model.layers.10.mlp.gate_proj.weight": 0.282528817653656, "model.layers.10.mlp.up_proj.weight": 0.31382155418395996, "model.layers.10.mlp.down_proj.weight": 0.3851136565208435, "model.layers.10.input_layernorm.weight": -0.04981499910354614, "model.layers.10.post_attention_layernorm.weight": 0.22835752367973328, "model.layers.11.self_attn.q_proj.weight": 0.22808925807476044, "model.layers.11.self_attn.k_proj.weight": 0.17264431715011597, "model.layers.11.self_attn.v_proj.weight": 0.35473909974098206, "model.layers.11.self_attn.o_proj.weight": 0.2214123159646988, "model.layers.11.mlp.gate_proj.weight": 0.34061092138290405, "model.layers.11.mlp.up_proj.weight": 0.3765887916088104, "model.layers.11.mlp.down_proj.weight": 0.4656827747821808, "model.layers.11.input_layernorm.weight": 0.07431256771087646, "model.layers.11.post_attention_layernorm.weight": 0.35051801800727844, "model.layers.12.self_attn.q_proj.weight": 0.16958221793174744, "model.layers.12.self_attn.k_proj.weight": 0.15682418644428253, "model.layers.12.self_attn.v_proj.weight": 0.3922196328639984, "model.layers.12.self_attn.o_proj.weight": 0.3203006684780121, "model.layers.12.mlp.gate_proj.weight": 0.47780460119247437, "model.layers.12.mlp.up_proj.weight": 0.4581189453601837, "model.layers.12.mlp.down_proj.weight": 0.4226323068141937, "model.layers.12.input_layernorm.weight": 0.06385652720928192, "model.layers.12.post_attention_layernorm.weight": 0.4944140911102295, "model.layers.13.self_attn.q_proj.weight": 0.08952601999044418, "model.layers.13.self_attn.k_proj.weight": 0.15269425511360168, "model.layers.13.self_attn.v_proj.weight": 0.3979102671146393, "model.layers.13.self_attn.o_proj.weight": 0.34557944536209106, "model.layers.13.mlp.gate_proj.weight": 0.5036556720733643, "model.layers.13.mlp.up_proj.weight": 0.46923378109931946, "model.layers.13.mlp.down_proj.weight": 0.46799930930137634, "model.layers.13.input_layernorm.weight": 0.2675913870334625, "model.layers.13.post_attention_layernorm.weight": 0.4959776997566223, "model.layers.14.self_attn.q_proj.weight": 0.24916835129261017, "model.layers.14.self_attn.k_proj.weight": 0.26207679510116577, "model.layers.14.self_attn.v_proj.weight": 0.273573100566864, "model.layers.14.self_attn.o_proj.weight": 0.24928902089595795, "model.layers.14.mlp.gate_proj.weight": 0.5173396468162537, "model.layers.14.mlp.up_proj.weight": 0.4814910590648651, "model.layers.14.mlp.down_proj.weight": 0.4825880229473114, "model.layers.14.input_layernorm.weight": 0.17111057043075562, "model.layers.14.post_attention_layernorm.weight": 0.12782183289527893, "model.layers.15.self_attn.q_proj.weight": 0.18505345284938812, "model.layers.15.self_attn.k_proj.weight": 0.07707730680704117, "model.layers.15.self_attn.v_proj.weight": 0.393758624792099, "model.layers.15.self_attn.o_proj.weight": 0.33833956718444824, "model.layers.15.mlp.gate_proj.weight": 0.4687366485595703, "model.layers.15.mlp.up_proj.weight": 0.7885865569114685, "model.layers.15.mlp.down_proj.weight": 0.5438224673271179, "model.layers.15.input_layernorm.weight": -0.13937383890151978, "model.layers.15.post_attention_layernorm.weight": 0.5844802856445312, "model.norm.weight": 0.5473131537437439}, "distance_from_C_to_P": {"model.embed_tokens.weight": 43.49333190917969, "model.layers.0.self_attn.q_proj.weight": 2.257699728012085, "model.layers.0.self_attn.k_proj.weight": 2.295138359069824, "model.layers.0.self_attn.v_proj.weight": 35.16324234008789, "model.layers.0.self_attn.o_proj.weight": 23.289461135864258, "model.layers.0.mlp.gate_proj.weight": 16.68465232849121, "model.layers.0.mlp.up_proj.weight": 19.24546241760254, "model.layers.0.mlp.down_proj.weight": 32.5025520324707, "model.layers.0.input_layernorm.weight": 4.389096260070801, "model.layers.0.post_attention_layernorm.weight": 2.2704086303710938, "model.layers.1.self_attn.q_proj.weight": 6.586032867431641, "model.layers.1.self_attn.k_proj.weight": 4.094926357269287, "model.layers.1.self_attn.v_proj.weight": 26.474950790405273, "model.layers.1.self_attn.o_proj.weight": 16.60353660583496, "model.layers.1.mlp.gate_proj.weight": 14.102926254272461, "model.layers.1.mlp.up_proj.weight": 18.02497673034668, "model.layers.1.mlp.down_proj.weight": 112.08307647705078, "model.layers.1.input_layernorm.weight": 0.7488248944282532, "model.layers.1.post_attention_layernorm.weight": 1.615445613861084, "model.layers.2.self_attn.q_proj.weight": 5.992092609405518, "model.layers.2.self_attn.k_proj.weight": 3.7792131900787354, "model.layers.2.self_attn.v_proj.weight": 22.52214241027832, "model.layers.2.self_attn.o_proj.weight": 13.939948081970215, "model.layers.2.mlp.gate_proj.weight": 12.871173858642578, "model.layers.2.mlp.up_proj.weight": 17.95098304748535, "model.layers.2.mlp.down_proj.weight": 19.500064849853516, "model.layers.2.input_layernorm.weight": 0.4208071827888489, "model.layers.2.post_attention_layernorm.weight": 1.3266652822494507, "model.layers.3.self_attn.q_proj.weight": 6.2170515060424805, "model.layers.3.self_attn.k_proj.weight": 5.1453447341918945, "model.layers.3.self_attn.v_proj.weight": 19.093549728393555, "model.layers.3.self_attn.o_proj.weight": 14.358773231506348, "model.layers.3.mlp.gate_proj.weight": 10.505334854125977, "model.layers.3.mlp.up_proj.weight": 19.928865432739258, "model.layers.3.mlp.down_proj.weight": 18.3585147857666, "model.layers.3.input_layernorm.weight": 1.7891039848327637, "model.layers.3.post_attention_layernorm.weight": 1.221595048904419, "model.layers.4.self_attn.q_proj.weight": 7.62687873840332, "model.layers.4.self_attn.k_proj.weight": 3.4369683265686035, "model.layers.4.self_attn.v_proj.weight": 15.325204849243164, "model.layers.4.self_attn.o_proj.weight": 16.065080642700195, "model.layers.4.mlp.gate_proj.weight": 8.604435920715332, "model.layers.4.mlp.up_proj.weight": 17.837129592895508, "model.layers.4.mlp.down_proj.weight": 17.19065284729004, "model.layers.4.input_layernorm.weight": 0.5497077703475952, "model.layers.4.post_attention_layernorm.weight": 1.0553209781646729, "model.layers.5.self_attn.q_proj.weight": 5.484812259674072, "model.layers.5.self_attn.k_proj.weight": 3.244459629058838, "model.layers.5.self_attn.v_proj.weight": 12.68348503112793, "model.layers.5.self_attn.o_proj.weight": 15.040936470031738, "model.layers.5.mlp.gate_proj.weight": 8.319960594177246, "model.layers.5.mlp.up_proj.weight": 14.603005409240723, "model.layers.5.mlp.down_proj.weight": 14.726249694824219, "model.layers.5.input_layernorm.weight": 0.47072386741638184, "model.layers.5.post_attention_layernorm.weight": 0.8973919153213501, "model.layers.6.self_attn.q_proj.weight": 6.517487049102783, "model.layers.6.self_attn.k_proj.weight": 3.2068417072296143, "model.layers.6.self_attn.v_proj.weight": 11.193802833557129, "model.layers.6.self_attn.o_proj.weight": 15.505904197692871, "model.layers.6.mlp.gate_proj.weight": 7.229670524597168, "model.layers.6.mlp.up_proj.weight": 12.239126205444336, "model.layers.6.mlp.down_proj.weight": 13.011250495910645, "model.layers.6.input_layernorm.weight": 0.557661235332489, "model.layers.6.post_attention_layernorm.weight": 0.7045776844024658, "model.layers.7.self_attn.q_proj.weight": 4.887880325317383, "model.layers.7.self_attn.k_proj.weight": 2.6773993968963623, "model.layers.7.self_attn.v_proj.weight": 9.680290222167969, "model.layers.7.self_attn.o_proj.weight": 13.013522148132324, "model.layers.7.mlp.gate_proj.weight": 7.260629177093506, "model.layers.7.mlp.up_proj.weight": 11.100801467895508, "model.layers.7.mlp.down_proj.weight": 12.064085960388184, "model.layers.7.input_layernorm.weight": 0.49268221855163574, "model.layers.7.post_attention_layernorm.weight": 0.7035426497459412, "model.layers.8.self_attn.q_proj.weight": 5.2889723777771, "model.layers.8.self_attn.k_proj.weight": 2.6346817016601562, "model.layers.8.self_attn.v_proj.weight": 10.759481430053711, "model.layers.8.self_attn.o_proj.weight": 11.407977104187012, "model.layers.8.mlp.gate_proj.weight": 6.769298076629639, "model.layers.8.mlp.up_proj.weight": 12.147845268249512, "model.layers.8.mlp.down_proj.weight": 12.151922225952148, "model.layers.8.input_layernorm.weight": 0.4407459497451782, "model.layers.8.post_attention_layernorm.weight": 0.6872392296791077, "model.layers.9.self_attn.q_proj.weight": 3.8521125316619873, "model.layers.9.self_attn.k_proj.weight": 2.594200372695923, "model.layers.9.self_attn.v_proj.weight": 10.252729415893555, "model.layers.9.self_attn.o_proj.weight": 9.749212265014648, "model.layers.9.mlp.gate_proj.weight": 6.577346324920654, "model.layers.9.mlp.up_proj.weight": 10.90256118774414, "model.layers.9.mlp.down_proj.weight": 12.704840660095215, "model.layers.9.input_layernorm.weight": 0.32476806640625, "model.layers.9.post_attention_layernorm.weight": 0.6889228224754333, "model.layers.10.self_attn.q_proj.weight": 4.564871311187744, "model.layers.10.self_attn.k_proj.weight": 3.2899324893951416, "model.layers.10.self_attn.v_proj.weight": 8.724952697753906, "model.layers.10.self_attn.o_proj.weight": 8.932331085205078, "model.layers.10.mlp.gate_proj.weight": 6.600856304168701, "model.layers.10.mlp.up_proj.weight": 10.40515422821045, "model.layers.10.mlp.down_proj.weight": 12.052450180053711, "model.layers.10.input_layernorm.weight": 0.3760976493358612, "model.layers.10.post_attention_layernorm.weight": 0.6661126017570496, "model.layers.11.self_attn.q_proj.weight": 2.8237571716308594, "model.layers.11.self_attn.k_proj.weight": 2.218452215194702, "model.layers.11.self_attn.v_proj.weight": 8.949543952941895, "model.layers.11.self_attn.o_proj.weight": 8.101017951965332, "model.layers.11.mlp.gate_proj.weight": 6.754951000213623, "model.layers.11.mlp.up_proj.weight": 9.997989654541016, "model.layers.11.mlp.down_proj.weight": 12.129905700683594, "model.layers.11.input_layernorm.weight": 0.3430231511592865, "model.layers.11.post_attention_layernorm.weight": 0.5214323997497559, "model.layers.12.self_attn.q_proj.weight": 3.175291061401367, "model.layers.12.self_attn.k_proj.weight": 1.9804635047912598, "model.layers.12.self_attn.v_proj.weight": 7.863048076629639, "model.layers.12.self_attn.o_proj.weight": 6.8674187660217285, "model.layers.12.mlp.gate_proj.weight": 7.543036460876465, "model.layers.12.mlp.up_proj.weight": 8.847228050231934, "model.layers.12.mlp.down_proj.weight": 11.474919319152832, "model.layers.12.input_layernorm.weight": 0.3300211727619171, "model.layers.12.post_attention_layernorm.weight": 0.49267223477363586, "model.layers.13.self_attn.q_proj.weight": 3.02225923538208, "model.layers.13.self_attn.k_proj.weight": 1.5455724000930786, "model.layers.13.self_attn.v_proj.weight": 7.098594665527344, "model.layers.13.self_attn.o_proj.weight": 6.161353588104248, "model.layers.13.mlp.gate_proj.weight": 8.362626075744629, "model.layers.13.mlp.up_proj.weight": 9.288451194763184, "model.layers.13.mlp.down_proj.weight": 13.151737213134766, "model.layers.13.input_layernorm.weight": 0.1903257966041565, "model.layers.13.post_attention_layernorm.weight": 0.5235737562179565, "model.layers.14.self_attn.q_proj.weight": 2.5497491359710693, "model.layers.14.self_attn.k_proj.weight": 1.9583373069763184, "model.layers.14.self_attn.v_proj.weight": 7.371973037719727, "model.layers.14.self_attn.o_proj.weight": 4.84598445892334, "model.layers.14.mlp.gate_proj.weight": 7.950356483459473, "model.layers.14.mlp.up_proj.weight": 8.24538516998291, "model.layers.14.mlp.down_proj.weight": 11.20811939239502, "model.layers.14.input_layernorm.weight": 0.48587706685066223, "model.layers.14.post_attention_layernorm.weight": 0.8542413711547852, "model.layers.15.self_attn.q_proj.weight": 3.2385640144348145, "model.layers.15.self_attn.k_proj.weight": 2.1247458457946777, "model.layers.15.self_attn.v_proj.weight": 6.112389087677002, "model.layers.15.self_attn.o_proj.weight": 9.004643440246582, "model.layers.15.mlp.gate_proj.weight": 8.966215133666992, "model.layers.15.mlp.up_proj.weight": 13.433892250061035, "model.layers.15.mlp.down_proj.weight": 17.848499298095703, "model.layers.15.input_layernorm.weight": 0.3989597260951996, "model.layers.15.post_attention_layernorm.weight": 0.8450830578804016, "model.norm.weight": 0.1970127820968628}}