{"stage": "pre-edit", "question_tag": "single_hop_efficacyq0", "question_type": "single_hop_efficacy", "id": "2hop__311694_129669", "question": "What is the place of birth of vera barbosa?", "answer": "Vila Franca de Xira", "answer_ids": [650, 10746, 31925, 936, 409, 1630, 9008, 128001], "n_tokens": 8.0, "log_prob": [-6.201605319976807, -5.604744911193848, -1.9706902503967285, -0.0041985465213656425, -1.1177009344100952, -0.7984957098960876, -0.3242357671260834, -0.30549973249435425]}
{"stage": "pre-edit", "question_tag": "single_hop_efficacyq1", "question_type": "single_hop_efficacy", "id": "2hop__311694_129669", "question": "In which state is vila franca de xira located?", "answer": "Lisbon District", "answer_ids": [81801, 11182, 128001], "n_tokens": 3.0, "log_prob": [-4.778216361999512, -8.025590896606445, -0.08863653987646103]}
{"stage": "pre-edit", "question_tag": "multi_hop_efficacyq0", "question_type": "multi_hop_efficacy", "id": "2hop__311694_129669", "question": "In which state is Vera Barbosa's place of birth located?", "answer": "Lisbon District", "answer_ids": [81801, 11182, 128001], "n_tokens": 3.0, "log_prob": [-6.828728675842285, -9.693164825439453, -0.1993931382894516]}
{"stage": "post-edit", "question_tag": "single_hop_efficacyq0", "question_type": "single_hop_efficacy", "id": "2hop__311694_129669", "question": "What is the place of birth of vera barbosa?", "answer": "Vila Franca de Xira", "answer_ids": [650, 10746, 31925, 936, 409, 1630, 9008, 128001], "n_tokens": 8.0, "log_prob": [-1.4785743951797485, -0.012597274035215378, -4.136476854910143e-05, -0.00017891713650897145, -0.0005346299149096012, -0.0006802152493037283, -0.001279250718653202, -2.2372121810913086]}
{"stage": "post-edit", "question_tag": "single_hop_efficacyq1", "question_type": "single_hop_efficacy", "id": "2hop__311694_129669", "question": "In which state is vila franca de xira located?", "answer": "Lisbon District", "answer_ids": [81801, 11182, 128001], "n_tokens": 3.0, "log_prob": [-1.9573248624801636, -0.8447574973106384, -3.6686441898345947]}
{"stage": "post-edit", "question_tag": "multi_hop_efficacyq0", "question_type": "multi_hop_efficacy", "id": "2hop__311694_129669", "question": "In which state is Vera Barbosa's place of birth located?", "answer": "Lisbon District", "answer_ids": [81801, 11182, 128001], "n_tokens": 3.0, "log_prob": [-4.505190372467041, -2.3425111770629883, -2.66916823387146]}
